pyexec.py
pyexec-1.1.1.dist-info/DESCRIPTION.rst
pyexec-1.1.1.dist-info/METADATA
pyexec-1.1.1.dist-info/RECORD
pyexec-1.1.1.dist-info/WHEEL
pyexec-1.1.1.dist-info/metadata.json
pyexec-1.1.1.dist-info/top_level.txt
