Metadata-Version: 1.1
Name: pyexec
Version: 1.1.1
Summary: Signal-triggered process reloader
Home-page: https://github.com/Arkq/pyexec
Author: Arkadiusz Bokowy
Author-email: arkadiusz.bokowy@gmail.com
License: MIT
Platform: UNKNOWN
Classifier: Intended Audience :: Developers
Classifier: License :: OSI Approved :: MIT License
Classifier: Programming Language :: Python :: 2
Classifier: Programming Language :: Python :: 3
Classifier: Topic :: Software Development :: Libraries
Classifier: Topic :: Utilities
